primosmath/__init__.py
primosmath-1.0.dist-info/LICENSE
primosmath-1.0.dist-info/METADATA
primosmath-1.0.dist-info/WHEEL
primosmath-1.0.dist-info/top_level.txt
primosmath-1.0.dist-info/RECORD
